passagemath_nauty/__init__.py
sage/all__sagemath_nauty.py
sage/libs/all__sagemath_nauty.py
sage/libs/nauty.cpython-310-aarch64-linux-gnu.so
sage/libs/nauty.pyx
sage_wheels/bin/NRswitchg
sage_wheels/bin/addedgeg
sage_wheels/bin/addptg
sage_wheels/bin/amtog
sage_wheels/bin/ancestorg
sage_wheels/bin/assembleg
sage_wheels/bin/biplabg
sage_wheels/bin/catg
sage_wheels/bin/complg
sage_wheels/bin/converseg
sage_wheels/bin/copyg
sage_wheels/bin/countg
sage_wheels/bin/countneg
sage_wheels/bin/cubhamg
sage_wheels/bin/deledgeg
sage_wheels/bin/delptg
sage_wheels/bin/dimacs2g
sage_wheels/bin/directg
sage_wheels/bin/dreadnaut
sage_wheels/bin/dretodot
sage_wheels/bin/dretog
sage_wheels/bin/edgetransg
sage_wheels/bin/genbg
sage_wheels/bin/genbgL
sage_wheels/bin/geng
sage_wheels/bin/gengL
sage_wheels/bin/genktreeg
sage_wheels/bin/genposetg
sage_wheels/bin/genquarticg
sage_wheels/bin/genrang
sage_wheels/bin/genspecialg
sage_wheels/bin/gentourng
sage_wheels/bin/gentreeg
sage_wheels/bin/hamheuristic
sage_wheels/bin/labelg
sage_wheels/bin/linegraphg
sage_wheels/bin/listg
sage_wheels/bin/multig
sage_wheels/bin/nbrhoodg
sage_wheels/bin/newedgeg
sage_wheels/bin/pickg
sage_wheels/bin/planarg
sage_wheels/bin/productg
sage_wheels/bin/ranlabg
sage_wheels/bin/ransubg
sage_wheels/bin/shortg
sage_wheels/bin/showg
sage_wheels/bin/subdivideg
sage_wheels/bin/twohamg
sage_wheels/bin/underlyingg
sage_wheels/bin/uniqg
sage_wheels/bin/vcolg
sage_wheels/bin/watercluster2
passagemath_nauty-10.6.43.dist-info/METADATA
passagemath_nauty-10.6.43.dist-info/WHEEL
passagemath_nauty-10.6.43.dist-info/top_level.txt
passagemath_nauty-10.6.43.dist-info/RECORD
